commits2pdf/__init__.py
commits2pdf/args.py
commits2pdf/cli.py
commits2pdf/commits.py
commits2pdf/constants.py
commits2pdf/logger.py
commits2pdf/render_cairo.py
commits2pdf/render_fpdf.py
commits2pdf-1.1.17.dist-info/LICENCE.md
commits2pdf-1.1.17.dist-info/METADATA
commits2pdf-1.1.17.dist-info/WHEEL
commits2pdf-1.1.17.dist-info/entry_points.txt
commits2pdf-1.1.17.dist-info/top_level.txt
commits2pdf-1.1.17.dist-info/RECORD
