Metadata-Version: 2.1
Name: commits2pdf
Version: 1.1.17
Summary: Convert Git commits to a PDF
Home-page: https://github.com/tomasvana10/commits2pdf
Author: Tomas Vana
License: MIT
Platform: any
Classifier: Topic :: Multimedia
Classifier: Development Status :: 5 - Production/Stable
Classifier: Environment :: Console
Classifier: Intended Audience :: End Users/Desktop
Classifier: Intended Audience :: Developers
Classifier: Intended Audience :: Education
Classifier: License :: OSI Approved :: MIT License
Classifier: Operating System :: OS Independent
Classifier: Programming Language :: Python
Classifier: Programming Language :: Python :: 3
Classifier: Topic :: Education
Classifier: Topic :: Office/Business
License-File: LICENCE.md
Requires-Dist: GitPython
Requires-Dist: fpdf
Requires-Dist: tqdm
Requires-Dist: pathvalidate
